descriptive_id/__init__.py
descriptive_id/fields.py
descriptive_id/models.py
descriptive_id-0.2.0.dist-info/DESCRIPTION.rst
descriptive_id-0.2.0.dist-info/METADATA
descriptive_id-0.2.0.dist-info/RECORD
descriptive_id-0.2.0.dist-info/WHEEL
descriptive_id-0.2.0.dist-info/metadata.json
descriptive_id-0.2.0.dist-info/top_level.txt
