Metadata-Version: 2.0
Name: descriptive-id
Version: 0.2.0
Summary: django-descriptive-id is a field that you can use on your models to give them a human-readable, unique identifier.
Home-page: https://github.com/bellhops/django-descriptive-id
Author: Bellhops
Author-email: tech@getbellhops.com
License: MIT
Download-URL: https://github.com/bellhops/django-descriptive-id/tarball/0.1
Keywords: django,modelfield,uuid
Platform: UNKNOWN
